androidtvremote/__init__.py
androidtvremote/adb.py
androidtvremote/remote.py
androidtvremote/utils.py
android_tv_remote-0.1.6.dist-info/AUTHORS.md
android_tv_remote-0.1.6.dist-info/LICENSE
android_tv_remote-0.1.6.dist-info/METADATA
android_tv_remote-0.1.6.dist-info/WHEEL
android_tv_remote-0.1.6.dist-info/top_level.txt
android_tv_remote-0.1.6.dist-info/RECORD
